[{"name":"menu","class":"menu"},{"name":"site","class":"admin-site"},{"name":"dashboard","class":"dashboard"},{"name":"post","class":"admin-post"},{"name":"media","class":"admin-media"},{"name":"links","class":"admin-links"},{"name":"page","class":"admin-page"},{"name":"comments","class":"admin-comments"},{"name":"appearance","class":"admin-appearance"},{"name":"plugins","class":"admin-plugins"},{"name":"users","class":"admin-users"},{"name":"tools","class":"admin-tools"},{"name":"settings","class":"admin-settings"},{"name":"network","class":"admin-network"},{"name":"home","class":"admin-home"},{"name":"generic","class":"admin-generic"},{"name":"collapse","class":"admin-collapse"},{"name":"filter","class":"filter"},{"name":"customizer","class":"admin-customizer"},{"name":"multisite","class":"admin-multisite"},{"name":"write blog","class":"welcome-write-blog"},{"name":"add page","class":"welcome-add-page"},{"name":"view site","class":"welcome-view-site"},{"name":"widgets and menus","class":"welcome-widgets-menus"},{"name":"comments","class":"welcome-comments"},{"name":"learn more","class":"welcome-learn-more"},{"name":"aside","class":"format-aside"},{"name":"image","class":"format-image"},{"name":"gallery","class":"format-gallery"},{"name":"video","class":"format-video"},{"name":"status","class":"format-status"},{"name":"quote","class":"format-quote"},{"name":"chat","class":"format-chat"},{"name":"audio","class":"format-audio"},{"name":"camera","class":"camera"},{"name":"images (alt)","class":"images-alt"},{"name":"images (alt 2)","class":"images-alt2"},{"name":"video (alt)","class":"video-alt"},{"name":"video (alt 2)","class":"video-alt2"},{"name":"video (alt 3)","class":"video-alt3"},{"name":"archive","class":"media-archive"},{"name":"audio","class":"media-audio"},{"name":"code","class":"media-code"},{"name":"default","class":"media-default"},{"name":"document","class":"media-document"},{"name":"interactive","class":"media-interactive"},{"name":"spreadsheet","class":"media-spreadsheet"},{"name":"text","class":"media-text"},{"name":"video","class":"media-video"},{"name":"audio playlist","class":"playlist-audio"},{"name":"video playlist","class":"playlist-video"},{"name":"play player","class":"controls-play"},{"name":"player pause","class":"controls-pause"},{"name":"player forward","class":"controls-forward"},{"name":"player skip forward","class":"controls-skipforward"},{"name":"player back","class":"controls-back"},{"name":"player skip back","class":"controls-skipback"},{"name":"player repeat","class":"controls-repeat"},{"name":"player volume on","class":"controls-volumeon"},{"name":"player volume off","class":"controls-volumeoff"},{"name":"crop","class":"image-crop"},{"name":"rotate","class":"image-rotate"},{"name":"rotate left","class":"image-rotate-left"},{"name":"rotate right","class":"image-rotate-right"},{"name":"flip vertical","class":"image-flip-vertical"},{"name":"flip horizontal","class":"image-flip-horizontal"},{"name":"filter","class":"image-filter"},{"name":"undo","class":"undo"},{"name":"redo","class":"redo"},{"name":"bold","class":"editor-bold"},{"name":"italic","class":"editor-italic"},{"name":"ul","class":"editor-ul"},{"name":"ol","class":"editor-ol"},{"name":"quote","class":"editor-quote"},{"name":"alignleft","class":"editor-alignleft"},{"name":"aligncenter","class":"editor-aligncenter"},{"name":"alignright","class":"editor-alignright"},{"name":"insertmore","class":"editor-insertmore"},{"name":"spellcheck","class":"editor-spellcheck"},{"name":"expand","class":"editor-expand"},{"name":"contract","class":"editor-contract"},{"name":"kitchen sink","class":"editor-kitchensink"},{"name":"underline","class":"editor-underline"},{"name":"justify","class":"editor-justify"},{"name":"textcolor","class":"editor-textcolor"},{"name":"paste","class":"editor-paste-word"},{"name":"paste","class":"editor-paste-text"},{"name":"remove formatting","class":"editor-removeformatting"},{"name":"video","class":"editor-video"},{"name":"custom character","class":"editor-customchar"},{"name":"outdent","class":"editor-outdent"},{"name":"indent","class":"editor-indent"},{"name":"help","class":"editor-help"},{"name":"strikethrough","class":"editor-strikethrough"},{"name":"unlink","class":"editor-unlink"},{"name":"rtl","class":"editor-rtl"},{"name":"break","class":"editor-break"},{"name":"code","class":"editor-code"},{"name":"paragraph","class":"editor-paragraph"},{"name":"table","class":"editor-table"},{"name":"align left","class":"align-left"},{"name":"align right","class":"align-right"},{"name":"align center","class":"align-center"},{"name":"align none","class":"align-none"},{"name":"lock","class":"lock"},{"name":"unlock","class":"unlock"},{"name":"calendar","class":"calendar"},{"name":"calendar","class":"calendar-alt"},{"name":"visibility","class":"visibility"},{"name":"hidden","class":"hidden"},{"name":"post status","class":"post-status"},{"name":"edit pencil","class":"edit"},{"name":"trash remove delete","class":"trash"},{"name":"sticky","class":"sticky"},{"name":"external","class":"external"},{"name":"arrow-up","class":"arrow-up"},{"name":"arrow-down","class":"arrow-down"},{"name":"arrow-right","class":"arrow-right"},{"name":"arrow-left","class":"arrow-left"},{"name":"arrow-up","class":"arrow-up-alt"},{"name":"arrow-down","class":"arrow-down-alt"},{"name":"arrow-right","class":"arrow-right-alt"},{"name":"arrow-left","class":"arrow-left-alt"},{"name":"arrow-up","class":"arrow-up-alt2"},{"name":"arrow-down","class":"arrow-down-alt2"},{"name":"arrow-right","class":"arrow-right-alt2"},{"name":"arrow-left","class":"arrow-left-alt2"},{"name":"sort","class":"sort"},{"name":"left right","class":"leftright"},{"name":"randomize shuffle","class":"randomize"},{"name":"list view","class":"list-view"},{"name":"exerpt view","class":"exerpt-view"},{"name":"grid view","class":"grid-view"},{"name":"share","class":"share"},{"name":"share","class":"share-alt"},{"name":"share","class":"share-alt2"},{"name":"twitter social","class":"twitter"},{"name":"rss","class":"rss"},{"name":"email","class":"email"},{"name":"email","class":"email-alt"},{"name":"facebook social","class":"facebook"},{"name":"facebook social","class":"facebook-alt"},{"name":"googleplus social","class":"googleplus"},{"name":"networking social","class":"networking"},{"name":"hammer development","class":"hammer"},{"name":"art design","class":"art"},{"name":"migrate migration","class":"migrate"},{"name":"performance","class":"performance"},{"name":"universal access accessibility","class":"universal-access"},{"name":"universal access accessibility","class":"universal-access-alt"},{"name":"tickets","class":"tickets"},{"name":"nametag","class":"nametag"},{"name":"clipboard","class":"clipboard"},{"name":"heart","class":"heart"},{"name":"megaphone","class":"megaphone"},{"name":"schedule","class":"schedule"},{"name":"wordpress","class":"wordpress"},{"name":"wordpress","class":"wordpress-alt"},{"name":"press this","class":"pressthis"},{"name":"update","class":"update"},{"name":"screenoptions","class":"screenoptions"},{"name":"info","class":"info"},{"name":"cart shopping","class":"cart"},{"name":"feedback form","class":"feedback"},{"name":"cloud","class":"cloud"},{"name":"translation language","class":"translation"},{"name":"tag","class":"tag"},{"name":"category","class":"category"},{"name":"archive","class":"archive"},{"name":"tagcloud","class":"tagcloud"},{"name":"text","class":"text"},{"name":"yes check checkmark","class":"yes"},{"name":"no x","class":"no"},{"name":"no x","class":"no-alt"},{"name":"plus add increase","class":"plus"},{"name":"plus add increase","class":"plus-alt"},{"name":"minus decrease","class":"minus"},{"name":"dismiss","class":"dismiss"},{"name":"marker","class":"marker"},{"name":"filled star","class":"star-filled"},{"name":"half star","class":"star-half"},{"name":"empty star","class":"star-empty"},{"name":"flag","class":"flag"},{"name":"warning","class":"warning"},{"name":"location pin","class":"location"},{"name":"location","class":"location-alt"},{"name":"vault safe","class":"vault"},{"name":"shield","class":"shield"},{"name":"shield","class":"shield-alt"},{"name":"sos help","class":"sos"},{"name":"search","class":"search"},{"name":"slides","class":"slides"},{"name":"analytics","class":"analytics"},{"name":"pie chart","class":"chart-pie"},{"name":"bar chart","class":"chart-bar"},{"name":"line chart","class":"chart-line"},{"name":"area chart","class":"chart-area"},{"name":"groups","class":"groups"},{"name":"businessman","class":"businessman"},{"name":"id","class":"id"},{"name":"id","class":"id-alt"},{"name":"products","class":"products"},{"name":"awards","class":"awards"},{"name":"forms","class":"forms"},{"name":"testimonial","class":"testimonial"},{"name":"portfolio","class":"portfolio"},{"name":"book","class":"book"},{"name":"book","class":"book-alt"},{"name":"download","class":"download"},{"name":"upload","class":"upload"},{"name":"backup","class":"backup"},{"name":"clock","class":"clock"},{"name":"lightbulb","class":"lightbulb"},{"name":"microphone mic","class":"microphone"},{"name":"desktop monitor","class":"desktop"},{"name":"tablet ipad","class":"tablet"},{"name":"smartphone iphone","class":"smartphone"},{"name":"phone","class":"phone"},{"name":"index card","class":"index-card"},{"name":"carrot food vendor","class":"carrot"},{"name":"building","class":"building"},{"name":"store","class":"store"},{"name":"album","class":"album"},{"name":"palm tree","class":"palmtree"},{"name":"tickets (alt)","class":"tickets-alt"},{"name":"money","class":"money"},{"name":"smiley smile","class":"smiley"},{"name":"thumbs up","class":"thumbs-up"},{"name":"thumbs down","class":"thumbs-down"},{"name":"layout","class":"layout"}]